cf_clearance2/__init__.py
cf_clearance2/errors.py
cf_clearance2/js/canvas.fingerprinting.js
cf_clearance2/js/chrome.global.js
cf_clearance2/js/chrome.plugin.js
cf_clearance2/js/chrome.runtime.js
cf_clearance2/js/emulate.touch.js
cf_clearance2/js/navigator.permissions.js
cf_clearance2/js/navigator.webdriver.js
cf_clearance2/retry.py
cf_clearance2/stealth.py
cf_clearance2-0.28.3.dist-info/METADATA
cf_clearance2-0.28.3.dist-info/WHEEL
cf_clearance2-0.28.3.dist-info/LICENSE
cf_clearance2-0.28.3.dist-info/RECORD
