Metadata-Version: 2.1
Name: cf-clearance2
Version: 0.28.3
Summary: Purpose To make a cloudflare challenge pass successfully, Can be use cf_clearance bypassed by cloudflare, However, with the cf_clearance, make sure you use the same IP and UA as when you got it.
Home-page: https://github.com/acheong08/cf_clearance
Author: vvanglro
Requires-Python: >=3.7,<4
Classifier: Programming Language :: Python :: 3
Classifier: Programming Language :: Python :: 3.7
Classifier: Programming Language :: Python :: 3.8
Classifier: Programming Language :: Python :: 3.9
Classifier: Programming Language :: Python :: 3.10
Classifier: Programming Language :: Python :: 3.11
Requires-Dist: playwright
Project-URL: Repository, https://github.com/acheong08/cf_clearance
